plonk/__init__.py
plonk/_config.py
plonk/_logging.py
plonk/_units.py
plonk/config.toml
plonk/__pycache__/__init__.cpython-39.pyc
plonk/__pycache__/_config.cpython-39.pyc
plonk/__pycache__/_logging.cpython-39.pyc
plonk/__pycache__/_units.cpython-39.pyc
plonk/analysis/__init__.py
plonk/analysis/discs.py
plonk/analysis/extra.py
plonk/analysis/filters.py
plonk/analysis/particles.py
plonk/analysis/profile.py
plonk/analysis/profiles.py
plonk/analysis/sinks.py
plonk/analysis/sph.py
plonk/analysis/total.py
plonk/analysis/__pycache__/__init__.cpython-39.pyc
plonk/analysis/__pycache__/discs.cpython-39.pyc
plonk/analysis/__pycache__/extra.cpython-39.pyc
plonk/analysis/__pycache__/filters.cpython-39.pyc
plonk/analysis/__pycache__/particles.cpython-39.pyc
plonk/analysis/__pycache__/profile.cpython-39.pyc
plonk/analysis/__pycache__/profiles.cpython-39.pyc
plonk/analysis/__pycache__/sinks.cpython-39.pyc
plonk/analysis/__pycache__/sph.cpython-39.pyc
plonk/analysis/__pycache__/total.cpython-39.pyc
plonk/simulation/__init__.py
plonk/simulation/_phantom_ev.py
plonk/simulation/simulation.py
plonk/simulation/time_series.py
plonk/simulation/__pycache__/__init__.cpython-39.pyc
plonk/simulation/__pycache__/_phantom_ev.cpython-39.pyc
plonk/simulation/__pycache__/simulation.cpython-39.pyc
plonk/simulation/__pycache__/time_series.cpython-39.pyc
plonk/snap/__init__.py
plonk/snap/context.py
plonk/snap/extra.py
plonk/snap/snap.py
plonk/snap/__pycache__/__init__.cpython-39.pyc
plonk/snap/__pycache__/context.cpython-39.pyc
plonk/snap/__pycache__/extra.cpython-39.pyc
plonk/snap/__pycache__/snap.cpython-39.pyc
plonk/snap/readers/__init__.py
plonk/snap/readers/phantom.py
plonk/snap/readers/__pycache__/__init__.cpython-39.pyc
plonk/snap/readers/__pycache__/phantom.cpython-39.pyc
plonk/utils/__init__.py
plonk/utils/kernels.py
plonk/utils/math.py
plonk/utils/snap.py
plonk/utils/strings.py
plonk/utils/visualize.py
plonk/utils/__pycache__/__init__.cpython-39.pyc
plonk-0.7.4.dist-info/LICENSE
plonk-0.7.4.dist-info/METADATA
plonk-0.7.4.dist-info/WHEEL
plonk-0.7.4.dist-info/top_level.txt
plonk-0.7.4.dist-info/RECORD
