Metadata-Version: 2.1
Name: plonk
Version: 0.7.4
Summary: Smoothed particle hydrodynamics analysis and visualization with Python.
Home-page: https://github.com/dmentipl/plonk
Author: Daniel Mentiplay
Author-email: daniel.mentiplay@protonmail.com
License: MIT
Platform: UNKNOWN
Classifier: Development Status :: 5 - Production/Stable
Classifier: License :: OSI Approved :: MIT License
Classifier: Programming Language :: Python :: 3.6
Classifier: Programming Language :: Python :: 3.7
Classifier: Programming Language :: Python :: 3.8
Classifier: Programming Language :: Python :: 3.9
Classifier: Programming Language :: Python :: 3.10
Classifier: Operating System :: OS Independent
Classifier: Topic :: Scientific/Engineering :: Astronomy
Classifier: Topic :: Scientific/Engineering :: Visualization
License-File: LICENSE
Requires-Dist: h5py
Requires-Dist: matplotlib
Requires-Dist: numba
Requires-Dist: numpy
Requires-Dist: pandas
Requires-Dist: pint (>=0.10.1)
Requires-Dist: scipy
Requires-Dist: toml
Provides-Extra: dev
Requires-Dist: black ; extra == 'dev'
Requires-Dist: coverage[toml] ; extra == 'dev'
Requires-Dist: coveralls ; extra == 'dev'
Requires-Dist: doc8 ; extra == 'dev'
Requires-Dist: flake8 ; extra == 'dev'
Requires-Dist: ipython ; extra == 'dev'
Requires-Dist: isort (>=5.0) ; extra == 'dev'
Requires-Dist: jupyterlab ; extra == 'dev'
Requires-Dist: mypy ; extra == 'dev'
Requires-Dist: myst-parser ; extra == 'dev'
Requires-Dist: pip ; extra == 'dev'
Requires-Dist: pydata-sphinx-theme ; extra == 'dev'
Requires-Dist: pydocstyle ; extra == 'dev'
Requires-Dist: pylint ; extra == 'dev'
Requires-Dist: pytest ; extra == 'dev'
Requires-Dist: sphinx ; extra == 'dev'
Requires-Dist: types-toml ; extra == 'dev'
Requires-Dist: twine ; extra == 'dev'
Provides-Extra: full
Requires-Dist: phantomconfig ; extra == 'full'
Requires-Dist: scikit-image (>=0.16) ; extra == 'full'
Requires-Dist: tqdm ; extra == 'full'
